{
  "id": "e31a347f",
  "url": "https://www.bilibili.com/video/BV1xa411X7Xr/?spm_id_from=333.1387.homepage.video_card.click&vd_source=ad236b930e655bdc87fa0b67763858b8",
  "platform": "B站",
  "status": "completed",
  "created_at": "2026-03-01 22:02:39",
  "updated_at": "2026-03-01 22:13:01",
  "subtitle_content": "🎼一个女人如果没有一项特长，你如何抓住男人的心？如果一个女人什么都不会的话，哎呀妈这都是贩外焦虑的。咱别说这东西影响，知道吧？这就啥也不会了，能怎么的？😡呃，不是咱们这边课程的话，嗯，小提琴、钢琴吉他都有的那这些课都什么价位呀？嗯，什么价位都有的。哎，我问一下咱们家孩子多大了，咱们家孩子哎呀，都说了，那些都是面向儿童的了，我看起来像我孩子一样吗？不像真的吗？真的哎呀你有点变成自由国辑了解一下。😊你多大，你叫我啊，姨我10后。🎼生活上。那你10后那不犯毛的，那吃了吗？😡🎼空。Yeah。他在干什么？他说他要学自由搏击。🎼你一下我。哎。哎。啊哎。哎。ふふふ。嘿嘿嘿，这回可没人敢管叫阿姨了，我早就不大呼了。哎，不错阿姨，对不起。😊是姐姐姐姐对不起啊，没关系没关系的。嗯。嗯。🎼开走开走。道了。こ。🎼 Yeah.🎼如果让你回到学生时代，你愿意回，操狗都不回。 🎼Yeah.",
  "subtitle_file": "G:\\mediaProjects\\fineSTEM\\projects\\up-video-analyzer\\data\\tasks\\e31a347f\\subtitles\\subtitle.txt",
  "error_message": null,
  "progress": 100,
  "download_size": null,
  "elapsed_time": 36.76800799369812,
  "analysis_result": {
    "word_freq": {
      "女人": 2,
      "一项": 1,
      "特长": 1,
      "抓住": 1,
      "男人": 1,
      "不会": 2,
      "的话": 2,
      "哎呀": 3,
      "贩外": 1,
      "焦虑": 1,
      "别说": 1,
      "东西": 1,
      "影响": 1,
      "知道": 1,
      "这边": 1,
      "课程": 1,
      "小提琴": 1,
      "钢琴": 1,
      "吉他": 1,
      "价位": 2,
      "一下": 3,
      "孩子": 3,
      "多大": 1,
      "面向": 1,
      "儿童": 1,
      "看起来": 1,
      "一样": 1,
      "不像": 1,
      "真的": 2,
      "变成": 1,
      "自由": 2,
      "国辑": 1,
      "了解": 1,
      "生活": 1,
      "不犯": 1,
      "Yeah": 3,
      "要学": 1,
      "搏击": 1,
      "这回": 1,
      "没人": 1,
      "敢管": 1,
      "阿姨": 2,
      "早就": 1,
      "不大呼": 1,
      "不错": 1,
      "对不起": 2,
      "姐姐": 2,
      "没关系": 2,
      "走开": 1,
      "回到": 1,
      "学生": 1,
      "时代": 1,
      "愿意": 1,
      "操狗": 1
    },
    "top_words": [
      [
        "哎呀",
        3
      ],
      [
        "一下",
        3
      ],
      [
        "孩子",
        3
      ],
      [
        "Yeah",
        3
      ],
      [
        "女人",
        2
      ],
      [
        "不会",
        2
      ],
      [
        "的话",
        2
      ],
      [
        "价位",
        2
      ],
      [
        "真的",
        2
      ],
      [
        "自由",
        2
      ],
      [
        "阿姨",
        2
      ],
      [
        "对不起",
        2
      ],
      [
        "姐姐",
        2
      ],
      [
        "没关系",
        2
      ],
      [
        "一项",
        1
      ],
      [
        "特长",
        1
      ],
      [
        "抓住",
        1
      ],
      [
        "男人",
        1
      ],
      [
        "贩外",
        1
      ],
      [
        "焦虑",
        1
      ]
    ],
    "total_words": 72,
    "unique_words": 54
  },
  "audio_file": "G:\\mediaProjects\\fineSTEM\\projects\\up-video-analyzer\\data\\tasks\\e31a347f\\audio\\audio.mp3",
  "video_file": null,
  "task_dir": "G:\\mediaProjects\\fineSTEM\\projects\\up-video-analyzer\\data\\tasks\\e31a347f"
}