{
  "created_at": "2026-07-05T01:09:40.451790",
  "created_by": "27fb2e88-bf95-4c98-b33b-688891d40f43",
  "updated_at": "2026-07-05T01:09:40.451790",
  "updated_by": null,
  "deleted_at": null,
  "deleted_by": null,
  "is_deleted": false,
  "type": "text_log",
  "title": "stage_07_execute",
  "content": "问题根源清楚了。页面中有硬编码的“进度序章”等文字在HTML中，而JS的引擎需要把这些替换掉才能用真实数据渲染。我现在生成一个完全纯净的单文件HTML，不依赖任何外部文件，所有CSS和JS内嵌在同一个文件中，彻底解决加载顺序和文件缺失问题。\n`html\n<!DOCTYPE html>\n<html lang=\"zh-CN\">\n<head>\n<meta charset=\"UTF-8\">\n<meta name=\"viewport\" content=\"width=device-width, initial-scale=1.0\">\n<title>奇幻选择之旅</title>\n<style>\n/* ===== 全局重置 & 基础 ===== */\n* { margin: 0; padding: 0; box-sizing: border-box; }\nbody {\nbackground: #0c0a1a;\ncolor: #e0d8f0;\nfont-family: 'Segoe UI', 'PingFang SC', Roboto, 'Helvetica Neue', sans-serif;\nmin",
  "content_url": null,
  "related_step": "stage_07_execute",
  "id": "f9bb6ba5-00a1-4c0d-b367-11f2350b4d57",
  "project_id": "b686df08-6655-4edb-a3a5-955f3244abe1",
  "author_id": "27fb2e88-bf95-4c98-b33b-688891d40f43"
}