{
  "created_at": "2026-07-04T07:40:38.281624",
  "created_by": "27fb2e88-bf95-4c98-b33b-688891d40f43",
  "updated_at": "2026-07-04T07:40:38.281624",
  "updated_by": null,
  "deleted_at": null,
  "deleted_by": null,
  "is_deleted": false,
  "type": "text_log",
  "title": "stage_07_execute",
  "content": "让我查看一下当前的项目状态。\n当前阶段：*stage_07_execute（执行阶段）*\n我们已经完成了：\n1. ✅ 技术选型（网页版）\n2. ✅ 设计文档\n3. ✅ 分步计划\n4. 🔄 *正在执行*具体代码编写\n刚才我把 `story_data.js` 写入了，*但还没写 `index.html`、`style.css` 和 `story_engine.js`*。接下来我的计划是：\n工具调用: skill_state_reader(success)",
  "content_url": null,
  "related_step": "stage_07_execute",
  "id": "32f37ab3-9f5e-4c78-a418-a78f0cffc006",
  "project_id": "b686df08-6655-4edb-a3a5-955f3244abe1",
  "author_id": "27fb2e88-bf95-4c98-b33b-688891d40f43"
}